mediapipe_viewer/__init__.py
mediapipe_viewer/__main__.py
mediapipe_viewer/config.py
mediapipe_viewer/pose/__init__.py
mediapipe_viewer/pose/mediapipe_pose.py
mediapipe_viewer/pose/mediapipe_pose_config.py
mediapipe_viewer/pose/mediapipe_pose_video.py
mediapipe_viewer/pose/mediapipe_pose_video_base.py
mediapipe_viewer/pose/mediapipe_pose_video_data.py
mediapipe_viewer/pose/mediapipe_pose_video_viewer.py
mediapipe_viewer-0.1.0.dist-info/METADATA
mediapipe_viewer-0.1.0.dist-info/WHEEL
mediapipe_viewer-0.1.0.dist-info/entry_points.txt
mediapipe_viewer-0.1.0.dist-info/RECORD
