Metadata-Version: 2.3
Name: mediapipe-viewer
Version: 0.1.0
Summary: MediaPipe Viewer..
Author-email: zhwuzhiguo <zhwuzhiguo@gmail.com>
Requires-Python: >=3.8
Requires-Dist: loguru>=0.7.2
Requires-Dist: mediapipe>=0.10.15
Requires-Dist: pydantic>=2.9.2
Requires-Dist: rerun-sdk>=0.19.0
